forechan/__init__.py
forechan/_da.py
forechan/broadcast.py
forechan/bufs.py
forechan/chan.py
forechan/context.py
forechan/mailbox.py
forechan/ops.py
forechan/pipe.py
forechan/pubsub.py
forechan/py.typed
forechan/select.py
forechan/selector.py
forechan/types.py
forechan/wait_group.py
forechan-0.2.10.dist-info/METADATA
forechan-0.2.10.dist-info/WHEEL
forechan-0.2.10.dist-info/top_level.txt
forechan-0.2.10.dist-info/RECORD
