Metadata-Version: 2.1
Name: forechan
Version: 0.2.10
Summary: Go style CSP for Python
Home-page: https://github.com/ms-jpq/forechan
Author: ms-jpq
Author-email: github@bigly.dog
License: UNKNOWN
Platform: UNKNOWN
Requires-Python: >=3.8.0
